lazyauto/__init__.py
lazyauto/Eda/__init__.py
lazyauto/Eda/eda.py
lazyauto/model_select/__init__.py
lazyauto/model_select/lazy_model_ev.py
lazyauto/model_select/lazy_model_ev_0.py
lazyauto/preperation/__init__.py
lazyauto/preperation/drop_outlier.py
lazyauto/time_transform/__init__.py
lazyauto/time_transform/date_time_transform.py
lazyauto-1.0.9.dist-info/AUTHORS.rst
lazyauto-1.0.9.dist-info/LICENSE
lazyauto-1.0.9.dist-info/METADATA
lazyauto-1.0.9.dist-info/WHEEL
lazyauto-1.0.9.dist-info/top_level.txt
lazyauto-1.0.9.dist-info/RECORD
